hamburger_pytorch/__init__.py
hamburger_pytorch/hamburger_pytorch.py
hamburger_pytorch-0.0.3.dist-info/LICENSE
hamburger_pytorch-0.0.3.dist-info/METADATA
hamburger_pytorch-0.0.3.dist-info/WHEEL
hamburger_pytorch-0.0.3.dist-info/top_level.txt
hamburger_pytorch-0.0.3.dist-info/RECORD
