Metadata-Version: 2.1
Name: hamburger-pytorch
Version: 0.0.3
Summary: Hamburger - Pytorch
Home-page: https://github.com/lucidrains/hamburger-pytorch
Author: Phil Wang
Author-email: lucidrains@gmail.com
License: MIT
Keywords: artificial intelligence,attention mechanism,matrix factorization
Platform: UNKNOWN
Classifier: Development Status :: 4 - Beta
Classifier: Intended Audience :: Developers
Classifier: Topic :: Scientific/Engineering :: Artificial Intelligence
Classifier: License :: OSI Approved :: MIT License
Classifier: Programming Language :: Python :: 3.6
Requires-Dist: torch
Requires-Dist: einops (>=0.3)
